pkg/__init__.py
pkg/sense_hat_adapter.py
pkg/sense_hat_device.py
pkg/sense_hat_imu_device.py
pkg/sense_hat_light_device.py
sense_hat_webthing-0.0.9.dist-info/LICENSE
sense_hat_webthing-0.0.9.dist-info/METADATA
sense_hat_webthing-0.0.9.dist-info/WHEEL
sense_hat_webthing-0.0.9.dist-info/top_level.txt
sense_hat_webthing-0.0.9.dist-info/RECORD
