Metadata-Version: 2.1
Name: sense-hat-webthing
Version: 0.0.9
Summary: Sense Hat WebThing
Home-page: https://github.com/rzr/sense-hat-webthing
Author: Philippe Coval
Author-email: rzr@users.sf.net
License: MPL-2.0
Project-URL: Source, https://github.com/rzr/sense-hat-webthing
Project-URL: Tracker, https://github.com/rzr/sense-hat-webthing/issues
Keywords: sensehat sense-hat RaspberryPi web thing webthing
Platform: UNKNOWN
Classifier: Intended Audience :: Developers
Classifier: License :: OSI Approved :: Mozilla Public License 2.0 (MPL 2.0)
Classifier: Programming Language :: Python :: 3.7
Requires-Python: >=3.7se, <4
Requires-Dist: sense-hat (==2.2.0)
